Metadata-Version: 2.1
Name: labelme-to-detectron2
Version: 0.0.1
Summary: labelme converter
Home-page: http://github.com/INF800/labelme_to_detectron2
Author: Asapanna Rakesh
Author-email: rakeshark22@gmail.com
License: Apache v2
Platform: UNKNOWN
License-File: LICENSE
